{"question":"Wer erfand das World Wide Web(www)?","answers":[{"correct":true,"text":"Tim Berners-Lee"},{"correct":false,"text":"Henry Ford"},{"correct":false,"text":"Marc Zuckerberg"},{"correct":false,"text":"Bill Gates"},{"correct":false,"text":"Albert Einstein"}],"id":1}
{"question":"Wer schrieb die Fantasy-Bücher \"Der Herr der Ringe 1-3\" und \"Der kleine Hobbit\"?","answers":[{"correct":false,"text":"Pete Johnson"},{"correct":false,"text":"Jeff Kinney"},{"correct":false,"text":"Joanne Kathleen Rowling"},{"correct":false,"text":"Johann Wolfgang von Goethe"},{"correct":true,"text":"John Ronald Reul Tolkien"}],"id":2}
{"question":"Hamburg ist die Hauptstadt von?","answers":[{"correct":false,"text":"Sachsen-Anhalt"},{"correct":false,"text":"Thüringen"},{"correct":true,"text":"Hamburg"},{"correct":false,"text":"Bayern"},{"correct":false,"text":"Mecklenburg-Vorpommern"}],"id":3}
{"question":"Wer wurde Fußballweltmeister 2014 (Herren)?","answers":[{"correct":false,"text":"Ghana"},{"correct":true,"text":"Schlaaaaand! (Deutschland)"},{"correct":false,"text":"Costa Rica"},{"correct":false,"text":"Argentinien"},{"correct":false,"text":"Brasilien"}],"id":4}
{"question":"Was heißt \"Hello\" auf deutsch?","answers":[{"correct":true,"text":"Hallo"},{"correct":false,"text":"Wie geht's dir?"},{"correct":false,"text":"Heute"},{"correct":false,"text":"Hell"},{"correct":false,"text":"Mir ist langweilig"}],"id":5}
{"question":"Das Wörtchen \"zum\" ist zusammengesetzt aus den Wörtern?","answers":[{"correct":false,"text":"\"zu\" und \"mum\""},{"correct":false,"text":"\"zu\", \"den\" und \"dummen\""},{"correct":true,"text":"\"zu\" und \"dem\""},{"correct":false,"text":"\"Zum\" ist ein eigenes Wort und ist nicht aus irgendwelchen anderen Wörtern zusammengestellt!"},{"correct":false,"text":"\"zu\" und \"denen\""}],"id":6}
{"question":"Die Mehrzahl von \"Atlas\" ist?","answers":[{"correct":false,"text":"Atlassen"},{"correct":false,"text":"Atlasseren"},{"correct":false,"text":"Atlas"},{"correct":false,"text":"Atlasse"},{"correct":true,"text":"Atlanten"}],"id":7}
{"question":"Welchen Beruf hat Angela Merkel?","answers":[{"correct":true,"text":"Bundeskanzlerin"},{"correct":false,"text":"Schreinerin"},{"correct":false,"text":"Bundestänzerin"},{"correct":false,"text":"Bürgermeisterin"},{"correct":false,"text":"Bundesanwältin"}],"id":8}
{"question":"Der Apfel fällt nicht weit vom?","answers":[{"correct":false,"text":"Gerüst"},{"correct":true,"text":"Stamm"},{"correct":false,"text":"Apfel"},{"correct":false,"text":"Kopf"},{"correct":false,"text":"Ast"}],"id":9}
{"question":"Wie heißt eine große und berühmte Fast Food-Kette?","answers":[{"correct":true,"text":"McDonald's"},{"correct":false,"text":"McDonald Duck"},{"correct":false,"text":"McDuck"},{"correct":false,"text":"McDonna's"},{"correct":false,"text":"Mc Fitty"}],"id":10}
